fastapi_cachetools/__init__.py
fastapi_cachetools-0.1.0.dist-info/LICENSE
fastapi_cachetools-0.1.0.dist-info/WHEEL
fastapi_cachetools-0.1.0.dist-info/METADATA
fastapi_cachetools-0.1.0.dist-info/RECORD
