Metadata-Version: 2.1
Name: fastapi-cachetools
Version: 0.1.0
Summary: Asynchronous cache library for FastAPI
Author-email: Sina Khorami <sinakhorami94@gmail.com>
Requires-Python: >=3.6
Classifier: License :: OSI Approved :: Apache Software License
Classifier: Programming Language :: Python :: 3
Classifier: Programming Language :: Python :: 3.6
Classifier: Programming Language :: Python :: 3.7
Classifier: Programming Language :: Python :: 3.8
Classifier: Programming Language :: Python :: 3.9
Classifier: Programming Language :: Python :: 3.10
Classifier: Programming Language :: Python :: 3.11
Project-URL: Home, https://github.com/SinaKhorami/fastapi-cachetools
